requirements/__init__.py
requirements/fragment.py
requirements/parser.py
requirements/py.typed
requirements/requirement.py
requirements/vcs.py
requirements_parser-0.12.0.dist-info/AUTHORS.md
requirements_parser-0.12.0.dist-info/LICENSE
requirements_parser-0.12.0.dist-info/METADATA
requirements_parser-0.12.0.dist-info/WHEEL
requirements_parser-0.12.0.dist-info/RECORD
