Metadata-Version: 2.3
Name: requirements-parser
Version: 0.12.0
Summary: This is a small Python module for parsing Pip requirement files.
License: Apache-2.0
Keywords: Pip,requirements,parse
Author: Paul Horton
Author-email: paul@hogr.dev
Maintainer: Paul Horton
Maintainer-email: paul@hogr.dev
Requires-Python: >=3.8,<4.0
Classifier: Development Status :: 5 - Production/Stable
Classifier: Intended Audience :: Developers
Classifier: Intended Audience :: Information Technology
Classifier: License :: OSI Approved :: Apache Software License
Classifier: Programming Language :: Python :: 3
Classifier: Programming Language :: Python :: 3.8
Classifier: Programming Language :: Python :: 3.9
Classifier: Programming Language :: Python :: 3.10
Classifier: Programming Language :: Python :: 3.11
Classifier: Programming Language :: Python :: 3.12
Classifier: Programming Language :: Python :: 3.13
Classifier: Programming Language :: Python :: 3.14
Classifier: Topic :: Software Development
Classifier: Topic :: Software Development :: Libraries :: Python Modules
Classifier: Topic :: System :: Software Distribution
Classifier: Typing :: Typed
Requires-Dist: packaging (>=23.2)
Project-URL: Bug Tracker, https://github.com/madpah/requirements-parser/issues
Project-URL: Documentation, https://requirements-parser.readthedocs.io/
Project-URL: Homepage, https://github.com/madpah/requirements-parser/#readme
Project-URL: Repository, https://github.com/madpah/requirements-parser
